powerbot_backtesting/__init__.py
powerbot_backtesting/data_analysis.py
powerbot_backtesting/exceptions/__init__.py
powerbot_backtesting/exceptions/backtesting_errors.py
powerbot_backtesting/models/__init__.py
powerbot_backtesting/models/backtesting_models.py
powerbot_backtesting/models/exporter_models.py
powerbot_backtesting/models/history_api_models.py
powerbot_backtesting/tests/config/__init__.py
powerbot_backtesting/tests/config/config.yml
powerbot_backtesting/tests/helpers/__init__.py
powerbot_backtesting/tests/helpers/cleanup.py
powerbot_backtesting/tests/helpers/conftest.py
powerbot_backtesting/utils/__init__.py
powerbot_backtesting/utils/constants.py
powerbot_backtesting/utils/helpers_backtesting.py
powerbot_backtesting/utils/helpers_general.py
powerbot_backtesting/utils/helpers_history.py
powerbot_backtesting/utils/helpers_processing.py
powerbot_backtesting/utils/utilities.py
powerbot_backtesting-2.0.17.dist-info/METADATA
powerbot_backtesting-2.0.17.dist-info/WHEEL
powerbot_backtesting-2.0.17.dist-info/pbr.json
powerbot_backtesting-2.0.17.dist-info/top_level.txt
powerbot_backtesting-2.0.17.dist-info/RECORD
