Metadata-Version: 2.1
Name: powerbot-backtesting
Version: 2.0.17
Summary: All PowerBot backtesting functions in one package
Home-page: https://github.com/powerbot-trading/powerbot_backtesting
Author: PowerBot Trading
Author-email: support@powerbot-trading.com
License: MIT
Platform: UNKNOWN
Requires-Python: >=3.9
Requires-Dist: atomicwrites >=1.4.0
Requires-Dist: attrs >=21.4.0
Requires-Dist: charset-normalizer >=2.0.12
Requires-Dist: colorama >=0.4.4
Requires-Dist: flake8 >=4.0.1
Requires-Dist: greenlet >=1.1.2
Requires-Dist: idna >=3.3
Requires-Dist: iniconfig >=1.1.1
Requires-Dist: mccabe >=0.6.0
Requires-Dist: numpy >=1.22.3
Requires-Dist: packaging >=21.0
Requires-Dist: pandas ==1.5.3
Requires-Dist: plotly >=5.6.0
Requires-Dist: pluggy >=1.0.0
Requires-Dist: powerbot-client >=2.4.2
Requires-Dist: pbr >=5.9.0
Requires-Dist: py >=1.11.0
Requires-Dist: pycodestyle >=2.8.0
Requires-Dist: pydantic ==1.10.6
Requires-Dist: pyflakes >=2.4.0
Requires-Dist: PyMySQL >=1.0.2
Requires-Dist: pyparsing >=3.0.7
Requires-Dist: pytest >=6.2.5
Requires-Dist: python-dateutil >=2.8.2
Requires-Dist: pytz >=2021.3
Requires-Dist: PyYAML >=6.0
Requires-Dist: requests >=2.27.1
Requires-Dist: six >=1.16.0
Requires-Dist: SQLAlchemy >=1.4.32
Requires-Dist: tenacity >=8.0.1
Requires-Dist: toml >=0.10.2
Requires-Dist: tqdm >=4.63.0
Requires-Dist: typing-extensions >=4.1.1
Requires-Dist: urllib3 >=1.26.8
